neon_phal_plugin_fan/__init__.py
neon_phal_plugin_fan-0.1.1.dist-info/LICENSE.md
neon_phal_plugin_fan-0.1.1.dist-info/METADATA
neon_phal_plugin_fan-0.1.1.dist-info/WHEEL
neon_phal_plugin_fan-0.1.1.dist-info/entry_points.txt
neon_phal_plugin_fan-0.1.1.dist-info/top_level.txt
neon_phal_plugin_fan-0.1.1.dist-info/RECORD
