Metadata-Version: 2.1
Name: neon-phal-plugin-fan
Version: 0.1.1
Summary: Fan Control Interface
Home-page: https://github.com/NeonGeckoCom/neon-phal-plugin-fan
Author: Neongecko
Author-email: developers@neon.ai
License: BSD-3
License-File: LICENSE.md
Requires-Dist: sj201-interface~=0.1
Requires-Dist: ovos-utils>=0.0.26,~=0.0
Requires-Dist: ovos-plugin-manager>=0.0.20,~=0.0
